{
  "tracks": [
    {
      "artist": "Travis Scott",
      "album": "Rodeo (Expanded Edition)",
      "track": "Maria I'm Drunk (feat. Justin Bieber & Young Thug)",
      "uri": "spotify:track:6Yqmv7XJLCrQEauMbPGZSw"
    },
    {
      "artist": "BLACKPINK",
      "album": "THE ALBUM",
      "track": "You Never Know",
      "uri": "spotify:track:39kzWAiVPpycdMpr745oPj"
    },
    {
      "artist": "Polo G",
      "album": "THE GOAT",
      "track": "I Know",
      "uri": "spotify:track:40j4RoqmLiivqzRObbQ4BF"
    },
    {
      "artist": "Taylor Swift",
      "album": "Lover",
      "track": "Cruel Summer",
      "uri": "spotify:track:1BxfuPKGuaTgP7aM0Bbdwr"
    },
    {
      "artist": "Kanye West",
      "album": "Champions",
      "track": "Champions",
      "uri": "spotify:track:2nBI3iWLhupR7LyAJ5GGkE"
    },
    {
      "artist": "ScHoolboy Q",
      "album": "CrasH Talk",
      "track": "Numb Numb Juice",
      "uri": "spotify:track:6tByydPskASjm9jTPkNQq0"
    },
    {
      "artist": "Kid Cudi",
      "album": "Man On The Moon III: The Chosen",
      "track": "Tequila Shots",
      "uri": "spotify:track:30KctD1WsHKTIYczXjip5a"
    },
    {
      "artist": "Kanye West",
      "album": "Graduation",
      "track": "Good Life",
      "uri": "spotify:track:4ZPdLEztrlZqbJkgHNw54L"
    },
    {
      "artist": "Meek Mill",
      "album": "Championships",
      "track": "Going Bad (feat. Drake)",
      "uri": "spotify:track:2IRZnDFmlqMuOrYOLnZZyc"
    },
    {
      "artist": "Chloe x Halle",
      "album": "Do It (feat. Doja Cat, City Girls & Mulatto) [Remix]",
      "track": "Do It (feat. Doja Cat, City Girls & Mulatto) [Remix]",
      "uri": "spotify:track:2WKJcMeqmjkL4FzFoJszR7"
    },
    {
      "artist": "King Von",
      "album": "Welcome to O'Block",
      "track": "Mine Too",
      "uri": "spotify:track:3ZWfkUYDt2SzVLgoNGPgbI"
    },
    {
      "artist": "Shawn Mendes",
      "album": "Monster",
      "track": "Monster (Shawn Mendes & Justin Bieber)",
      "uri": "spotify:track:2Z8yfpFX0ZMavHkcIeHiO1"
    },
    {
      "artist": "Alec Benjamin",
      "album": "These Two Windows",
      "track": "Demons",
      "uri": "spotify:track:57zRWXTQCFRV3zwg0NR8Ck"
    },
    {
      "artist": "Imagine Dragons",
      "album": "Evolve",
      "track": "Believer",
      "uri": "spotify:track:0pqnGHJpmpxLKifKRmU6WP"
    },
    {
      "artist": "H.E.R.",
      "album": "Slide (Remix) (feat. Pop Smoke, A Boogie Wit da Hoodie & Chris Brown) (feat. Pop Smoke)",
      "track": "Slide (Remix) (feat. Pop Smoke, A Boogie Wit da Hoodie & Chris Brown) (feat. Pop Smoke)",
      "uri": "spotify:track:6MO2bfLHKykUgCChFdw91H"
    },
    {
      "artist": "88rising",
      "album": "Head In The Clouds",
      "track": "Head In The Clouds",
      "uri": "spotify:track:3kYARoLSAvt86VFZ55BQcq"
    },
    {
      "artist": "Kid Travis",
      "album": "Strawberry Skies",
      "track": "Strawberry Skies",
      "uri": "spotify:track:458EaCXcB9TRBoJEDVcdcr"
    },
    {
      "artist": "A Boogie Wit da Hoodie",
      "album": "Artist",
      "track": "Still Think About You",
      "uri": "spotify:track:2FTeQQ5Rg9tBpgpTF5mnhE"
    },
    {
      "artist": "Frank Ocean",
      "album": "channel ORANGE",
      "track": "Lost",
      "uri": "spotify:track:3GZD6HmiNUhxXYf8Gch723"
    },
    {
      "artist": "Conan Gray",
      "album": "People Watching",
      "track": "People Watching",
      "uri": "spotify:track:4JeOesjcWWlprTAvucDSJX"
    },
    {
      "artist": "Migos",
      "album": "Culture III",
      "track": "Avalanche",
      "uri": "spotify:track:01BBYgKvjw5ye99zQTAK7P"
    },
    {
      "artist": "The Vamps",
      "album": "Meet The Vamps",
      "track": "Somebody To You",
      "uri": "spotify:track:6VrLYoQKdhu1Jruei06t65"
    },
    {
      "artist": "Taio Cruz",
      "album": "TY.O",
      "track": "There She Goes",
      "uri": "spotify:track:5g2lGWu4HTnNsSfo2Bruzr"
    },
    {
      "artist": "Baby Keem",
      "album": "The Melodic Blue",
      "track": "family ties (with Kendrick Lamar)",
      "uri": "spotify:track:3QFInJAm9eyaho5vBzxInN"
    },
    {
      "artist": "Imagine Dragons",
      "album": "Evolve",
      "track": "Whatever It Takes",
      "uri": "spotify:track:6Qn5zhYkTa37e91HC1D7lb"
    },
    {
      "artist": "dhruv",
      "album": "rapunzel",
      "track": "double take",
      "uri": "spotify:track:0QzuaeCEEOV40Pn7IvKEny"
    },
    {
      "artist": "Taylor Swift",
      "album": "Red (Taylor's Version)",
      "track": "Stay Stay Stay (Taylor's Version)",
      "uri": "spotify:track:7eQj6r5PIdYKEIZjucBMcq"
    },
    {
      "artist": "NEIKED",
      "album": "Better Days (NEIKED x Mae Muller x Polo G)",
      "track": "Better Days (NEIKED x Mae Muller x Polo G)",
      "uri": "spotify:track:6f5ExP43esnvdKPddwKXJH"
    },
    {
      "artist": "The Chainsmokers",
      "album": "World War Joy",
      "track": "Call You Mine",
      "uri": "spotify:track:2oejEp50ZzPuQTQ6v54Evp"
    },
    {
      "artist": "Chris Brown",
      "album": "Chris Brown (Expanded Edition)",
      "track": "Run It! (feat. Juelz Santana)",
      "uri": "spotify:track:7xYnUQigPoIDAMPVK79NEq"
    },
    {
      "artist": "Fresco Trey",
      "album": "Feel Good (feat. Lil Tjay)",
      "track": "Feel Good (feat. Lil Tjay)",
      "uri": "spotify:track:69FiPptnZd9ovg2tEJgBkN"
    },
    {
      "artist": "blackbear",
      "album": "everything means nothing",
      "track": "I felt that",
      "uri": "spotify:track:7KRaFRqbUbqfelHwmWyXuS"
    },
    {
      "artist": "Kane Brown",
      "album": "Be Like That",
      "track": "Be Like That - feat. Swae Lee & Khalid",
      "uri": "spotify:track:5f1joOtoMeyppIcJGZQvqJ"
    },
    {
      "artist": "Shaggy",
      "album": "Hot Shot",
      "track": "It Wasn't Me",
      "uri": "spotify:track:3WkibOpDF7cQ5xntM1epyf"
    },
    {
      "artist": "Cardi B",
      "album": "Please Me",
      "track": "Please Me",
      "uri": "spotify:track:0PG9fbaaHFHfre2gUVo7AN"
    },
    {
      "artist": "Taylor Swift",
      "album": "Lover",
      "track": "I Think He Knows",
      "uri": "spotify:track:2YWtcWi3a83pdEg3Gif4Pd"
    },
    {
      "artist": "Gryffin",
      "album": "Winnebago (feat. Quinn XCII & Daniel Wilson)",
      "track": "Winnebago (feat. Quinn XCII & Daniel Wilson)",
      "uri": "spotify:track:2FVm4ADgYRIQWlpYKDPdl9"
    },
    {
      "artist": "Joey Bada$$",
      "album": "ALL-AMERIKKKAN BADA$$",
      "track": "DEVASTATED",
      "uri": "spotify:track:4PnNzWe1LJoAMD5j5RHpI0"
    },
    {
      "artist": "Conan Gray",
      "album": "Kid Krow",
      "track": "Checkmate",
      "uri": "spotify:track:3SnpCALgmzVy7k07aAXbuA"
    },
    {
      "artist": "The Kid LAROI",
      "album": "F*CK LOVE (SAVAGE)",
      "track": "ALWAYS DO",
      "uri": "spotify:track:3QCU8BT0zDS9LPVfEhRFEE"
    },
    {
      "artist": "Kendrick Lamar",
      "album": "DAMN.",
      "track": "LOVE. FEAT. ZACARI.",
      "uri": "spotify:track:6PGoSes0D9eUDeeAafB2As"
    },
    {
      "artist": "Lost Frequencies",
      "album": "Where Are You Now",
      "track": "Where Are You Now",
      "uri": "spotify:track:3uUuGVFu1V7jTQL60S1r8z"
    },
    {
      "artist": "The Attire",
      "album": "Songs About Girls Like You",
      "track": "Girls Like You",
      "uri": "spotify:track:1h9cnXG82LBUy9l1FnYPCA"
    },
    {
      "artist": "Justin Bieber",
      "album": "My World 2.0",
      "track": "Eenie Meenie",
      "uri": "spotify:track:75vEuMA15pb8JmgrGugHEs"
    },
    {
      "artist": "Childish Gambino",
      "album": "Kauai",
      "track": "Pop Thieves (Make It Feel Good)",
      "uri": "spotify:track:77hL9s5AHzOhgXFxbLCdv1"
    },
    {
      "artist": "Andy Grammer",
      "album": "Fresh Eyes",
      "track": "Fresh Eyes",
      "uri": "spotify:track:7wahqDDzUPpJy91bVFHUF3"
    },
    {
      "artist": "Conan Gray",
      "album": "Telepath",
      "track": "Telepath",
      "uri": "spotify:track:3Z39gbqdaGL3WJXBG0gcuE"
    },
    {
      "artist": "Hannah Montana",
      "album": "Hannah Montana Forever",
      "track": "Gonna Get This",
      "uri": "spotify:track:1y6Y28gA3mNHSs7RDLrDKs"
    },
    {
      "artist": "Katy Perry",
      "album": "Never Really Over",
      "track": "Never Really Over",
      "uri": "spotify:track:5PYQUBXc7NYeI1obMKSJK0"
    },
    {
      "artist": "Alec Benjamin",
      "album": "These Two Windows",
      "track": "Match In The Rain",
      "uri": "spotify:track:08o7YsYkQXGjamCe9eDrrK"
    },
    {
      "artist": "Lil Tjay",
      "album": "Destined 2 Win",
      "track": "Move On - Bonus",
      "uri": "spotify:track:05WIYJYtnZHUmL1uuYmvY1"
    },
    {
      "artist": "Kanye West",
      "album": "My Beautiful Dark Twisted Fantasy",
      "track": "Gorgeous",
      "uri": "spotify:track:23SZWX2IaDnxmhFsSLvkG2"
    },
    {
      "artist": "Taylor Swift",
      "album": "Red (Taylor's Version)",
      "track": "The Very First Night (Taylor's Version) (From The Vault)",
      "uri": "spotify:track:6pYNq0ZwpPVazKzsqpf0G8"
    },
    {
      "artist": "Camila Cabello",
      "album": "Familia",
      "track": "Quiet",
      "uri": "spotify:track:665Prhaf0Ob6J6p7SKpaQE"
    },
    {
      "artist": "Little Mix",
      "album": "Get Weird",
      "track": "Black Magic",
      "uri": "spotify:track:6rmXhRIemCTPyMYZRDN7Qg"
    },
    {
      "artist": "Taylor Swift",
      "album": "Red (Taylor's Version)",
      "track": "Message In A Bottle (Taylor's Version) (From The Vault)",
      "uri": "spotify:track:3z6XUommYDWPHeFhmhhT6j"
    },
    {
      "artist": "Polo G",
      "album": "THE GOAT",
      "track": "Go Stupid",
      "uri": "spotify:track:4PklAHGXT5ityno3IA8SKd"
    },
    {
      "artist": "Lil Wayne",
      "album": "I Am Not A Human Being",
      "track": "Right Above It",
      "uri": "spotify:track:1kMuU3TNQvHbqvXCWBodmP"
    },
    {
      "artist": "Justin Bieber",
      "album": "My World 2.0",
      "track": "Baby",
      "uri": "spotify:track:6epn3r7S14KUqlReYr77hA"
    },
    {
      "artist": "blackbear",
      "album": "digital druglord",
      "track": "I miss the old u",
      "uri": "spotify:track:3jfFw63n74qkinjHibNPMS"
    },
    {
      "artist": "Kanye West",
      "album": "The Life Of Pablo",
      "track": "Ultralight Beam",
      "uri": "spotify:track:1eQBEelI2NCy7AUTerX0KS"
    },
    {
      "artist": "A.R. Rahman",
      "album": "Guru (Original Motion Picture Soundtrack)",
      "track": "Barso Re",
      "uri": "spotify:track:32DWojMZeZebVrfBkhAkKy"
    },
    {
      "artist": "blackbear",
      "album": "@ my worst",
      "track": "@ my worst",
      "uri": "spotify:track:0mHGftgYtmpH4y17T3VZ2E"
    },
    {
      "artist": "Selena Gomez",
      "album": "Back To You",
      "track": "Back To You - From 13 Reasons Why – Season 2 Soundtrack",
      "uri": "spotify:track:4hQ6UGyWQIGJmHSo0J88JW"
    },
    {
      "artist": "Justin Bieber",
      "album": "Believe",
      "track": "Beauty And A Beat",
      "uri": "spotify:track:190jyVPHYjAqEaOGmMzdyk"
    },
    {
      "artist": "Khalid",
      "album": "Up All Night",
      "track": "Up All Night",
      "uri": "spotify:track:1mpD5Q8IM32I4bF6eCpU74"
    },
    {
      "artist": "Kanye West",
      "album": "My Beautiful Dark Twisted Fantasy",
      "track": "Monster",
      "uri": "spotify:track:1ZHYJ2Wwgxes4m8Ba88PeK"
    },
    {
      "artist": "Bruno Mars",
      "album": "An Evening With Silk Sonic",
      "track": "777",
      "uri": "spotify:track:4zm8xZiV5FxJu62EHEvZaT"
    },
    {
      "artist": "Camila Cabello",
      "album": "Familia",
      "track": "psychofreak (feat. WILLOW)",
      "uri": "spotify:track:705dwKmZCd7ImAUyyD6Mpm"
    },
    {
      "artist": "Rod Wave",
      "album": "By Your Side",
      "track": "By Your Side",
      "uri": "spotify:track:2AaJeBEq3WLcfFW1y8svDf"
    },
    {
      "artist": "Chief Keef",
      "album": "Finally Rich",
      "track": "Love Sosa",
      "uri": "spotify:track:4IowQDUOzUvNtp72HMDcKO"
    },
    {
      "artist": "Imagine Dragons",
      "album": "Night Visions",
      "track": "Demons",
      "uri": "spotify:track:3LlAyCYU26dvFZBDUIMb7a"
    },
    {
      "artist": "Wes Walker",
      "album": "Jordan Belfort",
      "track": "Jordan Belfort",
      "uri": "spotify:track:6qMXubogFdMrvVMJwqATzd"
    },
    {
      "artist": "A Boogie Wit da Hoodie",
      "album": "Artist",
      "track": "Jungle",
      "uri": "spotify:track:5uZm7EFtP5aoTJvx5gv9Xf"
    },
    {
      "artist": "Drew Seeley",
      "album": "Another Cinderella Story",
      "track": "Just That Girl",
      "uri": "spotify:track:66zv9VF3nnL1UrsDRJQU9r"
    },
    {
      "artist": "Polo G",
      "album": "THE GOAT",
      "track": "Flex (feat. Juice WRLD)",
      "uri": "spotify:track:2QqJTIlGKRLJC3onkavYEz"
    },
    {
      "artist": "Trippie Redd",
      "album": "Trip At Knight",
      "track": "Rich MF (feat. Polo G & Lil Durk)",
      "uri": "spotify:track:6cUHiQEECDl5m3WFGQ1GCR"
    },
    {
      "artist": "Young Thug",
      "album": "So Much Fun",
      "track": "Hot (feat. Gunna)",
      "uri": "spotify:track:5Z8HZM6iQMhhqyPcCGY5g9"
    },
    {
      "artist": "Taylor Swift",
      "album": "Lover",
      "track": "I Forgot That You Existed",
      "uri": "spotify:track:43rA71bccXFGD4C8GOpIlN"
    },
    {
      "artist": "Ariana Grande",
      "album": "thank u, next",
      "track": "in my head",
      "uri": "spotify:track:4T652DlATVHe0jdLKaN3Bw"
    },
    {
      "artist": "Bruno Mars",
      "album": "Doo-Wops & Hooligans",
      "track": "Runaway Baby",
      "uri": "spotify:track:5MMLS3xm12D7N26xlfFApr"
    },
    {
      "artist": "Baby Bash",
      "album": "Suga Suga",
      "track": "Suga Suga",
      "uri": "spotify:track:14B2bUopOga5V3ypld7d6n"
    },
    {
      "artist": "Megan Thee Stallion",
      "album": "Suga",
      "track": "Captain Hook",
      "uri": "spotify:track:1E3VQQWFQAPJkXfYHjqWoI"
    },
    {
      "artist": "Chief Keef",
      "album": "Finally Rich",
      "track": "I Don't Like",
      "uri": "spotify:track:2ikkgfIIM9kGKZCXzXnTpj"
    },
    {
      "artist": "Summer Walker",
      "album": "Over It",
      "track": "Playing Games (with Bryson Tiller) - Extended Version",
      "uri": "spotify:track:2xyx0o4xNOLLjBSbOOdcbA"
    },
    {
      "artist": "Pop Smoke",
      "album": "Shoot For The Stars Aim For The Moon",
      "track": "Imperfections (Interlude)",
      "uri": "spotify:track:42er1na9BHF1ERol51wg8M"
    },
    {
      "artist": "Megan Thee Stallion",
      "album": "Good News",
      "track": "Cry Baby (feat. DaBaby)",
      "uri": "spotify:track:4aarlAfLKVCTxUDNgbwhjH"
    },
    {
      "artist": "blackbear",
      "album": "everything means nothing",
      "track": "queen of broken hearts",
      "uri": "spotify:track:1xyUCr7dIJYaUaaiDf4Q1L"
    },
    {
      "artist": "blackbear",
      "album": "everything means nothing",
      "track": "me & ur ghost",
      "uri": "spotify:track:5tiZBnx5IvETA0Pj3gELjn"
    },
    {
      "artist": "Playboi Carti",
      "album": "Die Lit",
      "track": "Fell In Luv (feat. Bryson Tiller)",
      "uri": "spotify:track:1s9DTymg5UQrdorZf43JQm"
    },
    {
      "artist": "Hannah Montana",
      "album": "Hannah Montana Forever",
      "track": "Barefoot Cinderella",
      "uri": "spotify:track:0AAa8J4ZDpN7AjZrfldP6X"
    },
    {
      "artist": "Megan Thee Stallion",
      "album": "Good News",
      "track": "Circles",
      "uri": "spotify:track:08TILUAN56HJoS1d9mNRty"
    },
    {
      "artist": "NIKI",
      "album": "Every Summertime",
      "track": "Every Summertime",
      "uri": "spotify:track:68HocO7fx9z0MgDU0ZPHro"
    },
    {
      "artist": "H.E.R.",
      "album": "Damage",
      "track": "Damage",
      "uri": "spotify:track:0KS2h61pHQ4WmOwruD7uxD"
    },
    {
      "artist": "Taylor Swift",
      "album": "Mr. Perfectly Fine (Taylor’s Version) (From The Vault)",
      "track": "Mr. Perfectly Fine (Taylor’s Version) (From The Vault)",
      "uri": "spotify:track:7l2tmgUhV7Y2aJHjiszifg"
    },
    {
      "artist": "Clinton Kane",
      "album": "CHICKEN TENDIES",
      "track": "CHICKEN TENDIES",
      "uri": "spotify:track:0awuNCj9gwJEM0seER22DW"
    },
    {
      "artist": "Meek Mill",
      "album": "Dreams Worth More Than Money",
      "track": "Bad for You (feat. Nicki Minaj)",
      "uri": "spotify:track:0HVba4HUwHnGlkHNitXMEL"
    },
    {
      "artist": "Shawn Mendes",
      "album": "Wonder",
      "track": "Wonder",
      "uri": "spotify:track:5KCbr5ndeby4y4ggthdiAb"
    },
    {
      "artist": "Megan Thee Stallion",
      "album": "Suga",
      "track": "Savage",
      "uri": "spotify:track:55CHeLEfn5iJ0IIkgaa4si"
    },
    {
      "artist": "Kanye West",
      "album": "The Life Of Pablo",
      "track": "Famous",
      "uri": "spotify:track:19a3JfW8BQwqHWUMbcqSx8"
    },
    {
      "artist": "Little Mix",
      "album": "Glory Days",
      "track": "Power (feat. Stormzy)",
      "uri": "spotify:track:4QVFtAswXqPoAWRLo5yu8a"
    },
    {
      "artist": "Alec Benjamin",
      "album": "These Two Windows",
      "track": "Must Have Been The Wind",
      "uri": "spotify:track:6lERHAmBCZmgODv3OYENXi"
    },
    {
      "artist": "Eminem",
      "album": "The Eminem Show",
      "track": "Without Me",
      "uri": "spotify:track:7lQ8MOhq6IN2w8EYcFNSUk"
    },
    {
      "artist": "Camila Cabello",
      "album": "Familia",
      "track": "Bam Bam (feat. Ed Sheeran)",
      "uri": "spotify:track:2DB4DdfCFMw1iaR6JaR03a"
    },
    {
      "artist": "Megan Thee Stallion",
      "album": "Suga",
      "track": "B.I.T.C.H.",
      "uri": "spotify:track:0xDUqQ3gVuhhjZnK9zXHwG"
    },
    {
      "artist": "Young Thug",
      "album": "Beautiful Thugger Girls",
      "track": "Relationship (feat. Future)",
      "uri": "spotify:track:25oOaleife6E2MIKmFkPvg"
    },
    {
      "artist": "Pitbull",
      "album": "Planet Pit (Deluxe Version)",
      "track": "Hey Baby (Drop It to the Floor) (feat. T-Pain)",
      "uri": "spotify:track:3rfhI32Il2hVRKDkuGeeen"
    },
    {
      "artist": "Kodak Black",
      "album": "FEMA (Finesse Elevate Motivate Achieve)",
      "track": "Heart Mind",
      "uri": "spotify:track:2OPxM2L3KtuehqY24vTMGs"
    },
    {
      "artist": "Alec Benjamin",
      "album": "These Two Windows",
      "track": "I'm Not A Cynic",
      "uri": "spotify:track:4iyGOU2Wtc7oNG4pm3taVd"
    },
    {
      "artist": "Hannah Montana",
      "album": "Hannah Montana Forever",
      "track": "Need a Little Love",
      "uri": "spotify:track:1Y8yf6EWrF1oSPkx0GtgvI"
    },
    {
      "artist": "syre",
      "album": "Daddy Issues - Slowed Remix",
      "track": "Daddy Issues - Slowed Remix",
      "uri": "spotify:track:1m8DugXfFgFTM6amX1VDMz"
    },
    {
      "artist": "Martin Garrix",
      "album": "Drown (feat. Clinton Kane)",
      "track": "Drown (feat. Clinton Kane)",
      "uri": "spotify:track:4RVtBlHFKj51Ipvpfv5ER4"
    },
    {
      "artist": "G.R.L.",
      "album": "G.R.L.",
      "track": "Rewind",
      "uri": "spotify:track:2Y5oYfwKgXTKsxZiw1KOtF"
    },
    {
      "artist": "Jordin Sparks",
      "album": "Jordin Sparks",
      "track": "No Air (feat. Chris Brown)",
      "uri": "spotify:track:1jUA4rb6ZCv4gby4YU53xq"
    },
    {
      "artist": "LISA",
      "album": "LALISA",
      "track": "MONEY",
      "uri": "spotify:track:7hU3IHwjX150XLoTVmjD0q"
    },
    {
      "artist": "Lil Durk",
      "album": "Broadway Girls (feat. Morgan Wallen)",
      "track": "Broadway Girls (feat. Morgan Wallen)",
      "uri": "spotify:track:3DZ8dbKg4OTSSqGARvecYd"
    },
    {
      "artist": "Ella Henderson",
      "album": "Chapter One (Deluxe Version)",
      "track": "Ghost",
      "uri": "spotify:track:4XPWKmy05Rcff6TLHNoNF8"
    },
    {
      "artist": "KYLE",
      "album": "Smyle",
      "track": "Don't Wanna Fall In Love",
      "uri": "spotify:track:1YakuHfzKxjnseCEeVQtrY"
    },
    {
      "artist": "Lil Tecca",
      "album": "We Love You Tecca 2",
      "track": "REPEAT IT (with Gunna)",
      "uri": "spotify:track:4s6vwFgPdCtidpEw8KuQT6"
    },
    {
      "artist": "NLE Choppa",
      "album": "Drop Shit",
      "track": "Drop Shit",
      "uri": "spotify:track:416XBAqBQECEjtMS8dlPQM"
    },
    {
      "artist": "Kanye West",
      "album": "The Life Of Pablo",
      "track": "Father Stretch My Hands Pt. 1",
      "uri": "spotify:track:4KW1lqgSr8TKrvBII0Brf8"
    },
    {
      "artist": "Megan Thee Stallion",
      "album": "Something for Thee Hotties",
      "track": "Thot Shit",
      "uri": "spotify:track:7FdmHr87G79PDRGy9SPBkZ"
    },
    {
      "artist": "Juice WRLD",
      "album": "Legends Never Die",
      "track": "Come & Go (with Marshmello)",
      "uri": "spotify:track:2Y0wPrPQBrGhoLn14xRYCG"
    },
    {
      "artist": "anees",
      "album": "sun and moon",
      "track": "sun and moon",
      "uri": "spotify:track:769Ld8demNhMgVLAQcjTDn"
    },
    {
      "artist": "Frank Ocean",
      "album": "Blonde",
      "track": "Pink + White",
      "uri": "spotify:track:3xKsf9qdS1CyvXSMEid6g8"
    },
    {
      "artist": "Freddie Stroma",
      "album": "A Cinderella Story: Once Upon A Song (Original Motion Picture Soundtrack)",
      "track": "Knockin",
      "uri": "spotify:track:7z3IUYrQzV37KEUVSSCo3M"
    },
    {
      "artist": "The Kid LAROI",
      "album": "F*CK LOVE 3: OVER YOU",
      "track": "NOT SOBER (feat. Polo G & Stunna Gambino)",
      "uri": "spotify:track:1JXBNvlDEl2epKSJ9EOgKX"
    },
    {
      "artist": "CNCO",
      "album": "Glory Days",
      "track": "Reggaetón Lento (Remix)",
      "uri": "spotify:track:5YH1A3YttSay4lgAR75tk3"
    },
    {
      "artist": "Megan Thee Stallion",
      "album": "Good News",
      "track": "Shots Fired",
      "uri": "spotify:track:3yhhv0VCmKkAWD9ysDLpTE"
    },
    {
      "artist": "Eminem",
      "album": "The Eminem Show",
      "track": "Cleanin' Out My Closet",
      "uri": "spotify:track:7BMO7O7ImjV8HNTH74Tshv"
    },
    {
      "artist": "blackbear",
      "album": "misery lake",
      "track": "u love u (with Tate McRae)",
      "uri": "spotify:track:0EFuHbkuin3pM6byX7VlGI"
    },
    {
      "artist": "Megan Thee Stallion",
      "album": "Suga",
      "track": "Rich",
      "uri": "spotify:track:0fdQue15BjCMA3ov14ubF4"
    },
    {
      "artist": "One Direction",
      "album": "FOUR",
      "track": "Steal My Girl",
      "uri": "spotify:track:2Bs4jQEGMycglOfWPBqrVG"
    },
    {
      "artist": "Alec Benjamin",
      "album": "These Two Windows",
      "track": "Mind Is A Prison",
      "uri": "spotify:track:2hGQDYmjkwTS0J7Q2bM2sF"
    },
    {
      "artist": "Pritam",
      "album": "Yeh Jawaani Hai Deewani",
      "track": "Balam Pichkari",
      "uri": "spotify:track:18e3XXYCv4Tx8uUl1mP3CN"
    },
    {
      "artist": "2Pac",
      "album": "Greatest Hits",
      "track": "California Love - Original Version",
      "uri": "spotify:track:3ia3dJETSOllPsv3LJkE35"
    },
    {
      "artist": "Eminem",
      "album": "The Eminem Show",
      "track": "Square Dance",
      "uri": "spotify:track:27mgDrExPa3obPAYXd3yQg"
    },
    {
      "artist": "JAY-Z",
      "album": "The Blueprint 3",
      "track": "Run This Town",
      "uri": "spotify:track:7LR85XLWw2yXqKBSI5brbG"
    },
    {
      "artist": "G.R.L.",
      "album": "G.R.L.",
      "track": "Ugly Heart",
      "uri": "spotify:track:3qqho4PnTn3zlMPBzWhFFD"
    },
    {
      "artist": "Alec Benjamin",
      "album": "These Two Windows",
      "track": "Jesus in LA",
      "uri": "spotify:track:0uLPKDuIhkIhttiwezNdiG"
    },
    {
      "artist": "One Direction",
      "album": "Take Me Home",
      "track": "They Don't Know About Us",
      "uri": "spotify:track:6M31fPFCYB8Job3MCjjrDV"
    },
    {
      "artist": "Polo G",
      "album": "Hall of Fame 2.0",
      "track": "Bad Man (Smooth Criminal)",
      "uri": "spotify:track:62l3NSQPUxvcwwzKUmysrE"
    },
    {
      "artist": "Justin Bieber",
      "album": "My World 2.0",
      "track": "That Should Be Me",
      "uri": "spotify:track:0aPZbnkMoWJaJ5CNVLCj8S"
    },
    {
      "artist": "Drake",
      "album": "Dark Lane Demo Tapes",
      "track": "Time Flies",
      "uri": "spotify:track:5H4mXWKcicuLKDn4Jy0sK7"
    },
    {
      "artist": "Rex Orange County",
      "album": "Bcos U Will Never B Free",
      "track": "Corduroy Dreams",
      "uri": "spotify:track:02tvc9CFnTyHuSRlGeNv9w"
    },
    {
      "artist": "Rod Wave",
      "album": "Pray 4 Love",
      "track": "Rags2Riches 2 (feat. Lil Baby)",
      "uri": "spotify:track:0qJeyYAgv6UpvewUxRXAhb"
    },
    {
      "artist": "Tate McRae",
      "album": "i used to think i could fly",
      "track": "what would you do?",
      "uri": "spotify:track:4ewmHD3aRBmLyTsbGreNLw"
    },
    {
      "artist": "blackbear",
      "album": "everything means nothing",
      "track": "hot girl bummer",
      "uri": "spotify:track:6jRq8gaZhMUyy5RclRPcAf"
    },
    {
      "artist": "Meek Mill",
      "album": "Championships",
      "track": "On Me (feat. Cardi B)",
      "uri": "spotify:track:3DnZfpfe8wLeJgzc00gKeW"
    },
    {
      "artist": "Polo G",
      "album": "THE GOAT",
      "track": "21",
      "uri": "spotify:track:3JKgcAa7r07ocVWcV8bS0H"
    },
    {
      "artist": "Imagine Dragons",
      "album": "Evolve",
      "track": "Thunder",
      "uri": "spotify:track:1zB4vmk8tFRmM9UULNzbLB"
    },
    {
      "artist": "Maroon 5",
      "album": "V",
      "track": "Animals",
      "uri": "spotify:track:2bL2gyO6kBdLkNSkxXNh6x"
    },
    {
      "artist": "Bruno Mars",
      "album": "Smokin Out The Window",
      "track": "Smokin Out The Window",
      "uri": "spotify:track:4iN16F8JtVxG2UTzp3avGl"
    },
    {
      "artist": "Dybbukk",
      "album": "It's Not so Bad",
      "track": "It's Not so Bad",
      "uri": "spotify:track:0DTKMbjhF2Ejca85w1Ivpl"
    },
    {
      "artist": "Usher",
      "album": "Confessions (Expanded Edition)",
      "track": "Burn",
      "uri": "spotify:track:7z3N2W7Xz1t2G2sAO8wFVH"
    },
    {
      "artist": "YBN Nahmir",
      "album": "VISIONLAND",
      "track": "Opp Stoppa (feat. 21 Savage)",
      "uri": "spotify:track:78p1rF7xx1snnaKxtUzBHn"
    },
    {
      "artist": "Polo G",
      "album": "THE GOAT",
      "track": "Heartless (feat. Mustard)",
      "uri": "spotify:track:2iP3unJbxZvRuqyrS0ocZy"
    },
    {
      "artist": "Taio Cruz",
      "album": "The Rokstarr Hits Collection",
      "track": "Break Your Heart",
      "uri": "spotify:track:7ElF5zxOwYP4qVSWVvse3W"
    },
    {
      "artist": "CKay",
      "album": "CKay The First",
      "track": "love nwantiti (ah ah ah)",
      "uri": "spotify:track:2Xr1dTzJee307rmrkt8c0g"
    },
    {
      "artist": "Summer Walker",
      "album": "No Love (with SZA & Cardi B)",
      "track": "No Love (with SZA & Cardi B) - Extended Version",
      "uri": "spotify:track:0IMUFRaM2W3wKNM1CSQ4Zm"
    },
    {
      "artist": "Taylor Swift",
      "album": "1989",
      "track": "Bad Blood",
      "uri": "spotify:track:273dCMFseLcVsoSWx59IoE"
    },
    {
      "artist": "A$AP Rocky",
      "album": "LIVE.LOVE.A$AP",
      "track": "Sandman",
      "uri": "spotify:track:0qkA0NU7cDKWkFXNGRcNaB"
    },
    {
      "artist": "Frank Ocean",
      "album": "In My Room",
      "track": "In My Room",
      "uri": "spotify:track:4S4Mfvv03M1cHgIOJcbUCL"
    },
    {
      "artist": "Lil Peep",
      "album": "Come Over When You're Sober, Pt. 2",
      "track": "Falling Down - Bonus Track",
      "uri": "spotify:track:4jvjzW7Hm0yK4LvvE0Paz9"
    },
    {
      "artist": "Kanye West",
      "album": "Graduation",
      "track": "I Wonder",
      "uri": "spotify:track:7rbECVPkY5UODxoOUVKZnA"
    },
    {
      "artist": "Polo G",
      "album": "THE GOAT",
      "track": "Martin & Gina",
      "uri": "spotify:track:1VLtjHwRWOVJiE5Py7JxoQ"
    },
    {
      "artist": "Lauv",
      "album": "I met you when I was 18. (the playlist)",
      "track": "I Like Me Better",
      "uri": "spotify:track:2P91MQbaiQOfbiz9VqhqKQ"
    },
    {
      "artist": "Ariana Grande",
      "album": "boyfriend",
      "track": "boyfriend (with Social House)",
      "uri": "spotify:track:0Ryd8975WihbObpp5cPW1t"
    },
    {
      "artist": "Powfu",
      "album": "Some Boring, Love Stories",
      "track": "I Can't Sleep",
      "uri": "spotify:track:25yup6WYnPoITrfzhkBLmt"
    },
    {
      "artist": "Bruno Mars",
      "album": "That's What I Like (feat. Gucci Mane)",
      "track": "That's What I Like (feat. Gucci Mane)",
      "uri": "spotify:track:1BEMASUZQDqN5UGxMb1m6A"
    },
    {
      "artist": "Lil Durk",
      "album": "Still Trappin'",
      "track": "Still Trappin'",
      "uri": "spotify:track:0JW0lLXMDe7l9d3ULj8PJX"
    },
    {
      "artist": "Pitbull",
      "album": "Planet Pit (Deluxe Version)",
      "track": "International Love (feat. Chris Brown)",
      "uri": "spotify:track:62zFEHfAYl5kdHYOivj4BC"
    },
    {
      "artist": "Sleepy Hallow",
      "album": "Still Sleep?",
      "track": "2055",
      "uri": "spotify:track:4XvcHTUfIlWfyJTRG0aqlo"
    },
    {
      "artist": "Lauv",
      "album": "~how i'm feeling~",
      "track": "i'm so tired...",
      "uri": "spotify:track:4vjpLMyL3ZO6aphdYr8XYw"
    },
    {
      "artist": "Blxst",
      "album": "No Love Lost",
      "track": "Chosen (feat. Ty Dolla $ign)",
      "uri": "spotify:track:1dIWPXMX4kRHj6Dt2DStUQ"
    },
    {
      "artist": "The Weeknd",
      "album": "Dawn FM",
      "track": "Out of Time",
      "uri": "spotify:track:2SLwbpExuoBDZBpjfefCtV"
    },
    {
      "artist": "King Von",
      "album": "Took Her To The O",
      "track": "Took Her To The O",
      "uri": "spotify:track:0kSnpKOS1bUguBGe2z661G"
    },
    {
      "artist": "Justin Bieber",
      "album": "My World",
      "track": "Favorite Girl",
      "uri": "spotify:track:4nTjkWK590oBDcnIxTr1mI"
    },
    {
      "artist": "Meek Mill",
      "album": "Championships",
      "track": "Championships",
      "uri": "spotify:track:5DTOk0tCrmicVQP4mc6hkr"
    },
    {
      "artist": "Taylor Swift",
      "album": "Red (Taylor's Version)",
      "track": "Starlight (Taylor's Version)",
      "uri": "spotify:track:7A2cNLRT0YJc1yjxHlKihs"
    },
    {
      "artist": "A Boogie Wit da Hoodie",
      "album": "Artist 2.0",
      "track": "Me and My Guitar",
      "uri": "spotify:track:6cZH4rX1KTt1aJ3Ql6Ynja"
    },
    {
      "artist": "Forrest.",
      "album": "Lately",
      "track": "Lately",
      "uri": "spotify:track:5awvelCGpDQHwgZem0ira9"
    },
    {
      "artist": "Future",
      "album": "I NEVER LIKED YOU",
      "track": "WAIT FOR U (feat. Drake & Tems)",
      "uri": "spotify:track:59nOXPmaKlBfGMDeOVGrIK"
    },
    {
      "artist": "Alec Benjamin",
      "album": "These Two Windows",
      "track": "The Book of You & I",
      "uri": "spotify:track:2CSrG5fnBpcdfPXg7sJUBi"
    },
    {
      "artist": "Kendrick Lamar",
      "album": "Mr. Morale & The Big Steppers",
      "track": "Die Hard",
      "uri": "spotify:track:6gI9b2VsoWhjhIuIeToDVs"
    },
    {
      "artist": "J. Cole",
      "album": "Born Sinner",
      "track": "Crooked Smile (feat. TLC)",
      "uri": "spotify:track:5gFoAVTN9YlM9uJCrFZtgl"
    },
    {
      "artist": "Taylor Swift",
      "album": "Red (Taylor's Version)",
      "track": "All Too Well (Taylor's Version)",
      "uri": "spotify:track:3nsfB1vus2qaloUdcBZvDu"
    },
    {
      "artist": "Quality Control",
      "album": "Quality Control: Control The Streets Volume 2",
      "track": "Leave Em Alone (Layton Greene, Lil Baby feat. City Girls, PnB Rock)",
      "uri": "spotify:track:6Vdyu21iT8qScU1haSjWUU"
    },
    {
      "artist": "Camila Cabello",
      "album": "Familia",
      "track": "La Buena Vida",
      "uri": "spotify:track:47bzJjh9bAbo3s3NHSK4r8"
    },
    {
      "artist": "T-Pain",
      "album": "Epiphany",
      "track": "Buy U a Drank (Shawty Snappin') (feat. Yung Joc)",
      "uri": "spotify:track:1tkMs9wDPknQ3ZHcKDw1ES"
    },
    {
      "artist": "Dove Cameron",
      "album": "Boyfriend",
      "track": "Boyfriend",
      "uri": "spotify:track:59CfNbkERJ3NoTXDvoURjj"
    },
    {
      "artist": "Hannah Montana",
      "album": "Hannah Montana Forever",
      "track": "I'm Still Good",
      "uri": "spotify:track:5NdwMwDT64WOqpi6XbOtqP"
    },
    {
      "artist": "OneRepublic",
      "album": "I Ain’t Worried",
      "track": "I Ain't Worried",
      "uri": "spotify:track:4h9wh7iOZ0GGn8QVp4RAOB"
    },
    {
      "artist": "Polo G",
      "album": "Hall of Fame",
      "track": "Clueless (with Pop Smoke & Fivio Foreign)",
      "uri": "spotify:track:4CPcZHzSvIBM8AKhdHUwnL"
    },
    {
      "artist": "Miley Cyrus",
      "album": "Meet Miley Cyrus",
      "track": "See You Again",
      "uri": "spotify:track:3AjyOYxBv8bByfBtG5o9dP"
    },
    {
      "artist": "Nicky Youre",
      "album": "Sunroof",
      "track": "Sunroof",
      "uri": "spotify:track:3RfTeIrWS8LNrfHYwechtt"
    },
    {
      "artist": "Playboi Carti",
      "album": "Whole Lotta Red",
      "track": "Sky",
      "uri": "spotify:track:29TPjc8wxfz4XMn21O7VsZ"
    },
    {
      "artist": "Coco Jones",
      "album": "Let It Shine",
      "track": "Me And You",
      "uri": "spotify:track:33pEKWX4isAp2xAp82gzbj"
    },
    {
      "artist": "Frank Ocean",
      "album": "channel ORANGE",
      "track": "Lost",
      "uri": "spotify:track:4L7jMAP8UcIe309yQmkdcO"
    },
    {
      "artist": "Megan Thee Stallion",
      "album": "Good News",
      "track": "What’s New",
      "uri": "spotify:track:3jRHehB5ulTMKfK5WaqDqc"
    },
    {
      "artist": "Alec Benjamin",
      "album": "These Two Windows",
      "track": "Oh My God",
      "uri": "spotify:track:44I5NYJ7CGEcaLOuG2zJsU"
    },
    {
      "artist": "Nicky Youre",
      "album": "Sunroof",
      "track": "Sunroof",
      "uri": "spotify:track:4h4QlmocP3IuwYEj2j14p8"
    },
    {
      "artist": "Travis Scott",
      "album": "ASTROWORLD",
      "track": "WAKE UP",
      "uri": "spotify:track:20MuVazoNMv6xjKPnRFOxG"
    },
    {
      "artist": "NLE Choppa",
      "album": "Jumpin (feat. Polo G)",
      "track": "Jumpin (feat. Polo G)",
      "uri": "spotify:track:1z7LV5wkExwW8YJk0IrPUA"
    },
    {
      "artist": "XXXTENTACION",
      "album": "Bad Vibes Forever",
      "track": "bad vibes forever",
      "uri": "spotify:track:03eJ2DclFWXYU8GWgANdmZ"
    },
    {
      "artist": "Kanye West",
      "album": "Graduation",
      "track": "Champion",
      "uri": "spotify:track:0sL1Fj3zQlF7tbHVNiDUgw"
    },
    {
      "artist": "Farruko",
      "album": "Pepas",
      "track": "Pepas",
      "uri": "spotify:track:5fwSHlTEWpluwOM0Sxnh5k"
    },
    {
      "artist": "Taylor Swift",
      "album": "evermore",
      "track": "no body, no crime (feat. HAIM)",
      "uri": "spotify:track:3RaT22zZsxVYxxKR7TAaYF"
    },
    {
      "artist": "BLACKPINK",
      "album": "SQUARE UP",
      "track": "Forever Young",
      "uri": "spotify:track:6veFyjNycn6EaNCKhkPXUY"
    },
    {
      "artist": "Clinton Kane",
      "album": "i don't want to watch the world end with someone else",
      "track": "i don't want to watch the world end with someone else",
      "uri": "spotify:track:58qX77t2VWMWcycsh9zKLc"
    },
    {
      "artist": "Sleepy Hallow",
      "album": "Die Young (feat. 347aidan)",
      "track": "Die Young (feat. 347aidan)",
      "uri": "spotify:track:6EbVuwU7EnKeF2hdpViXCH"
    },
    {
      "artist": "5 Seconds of Summer",
      "album": "5 Seconds Of Summer",
      "track": "She Looks So Perfect",
      "uri": "spotify:track:1gugDOSMREb34Xo0c1PlxM"
    },
    {
      "artist": "blackbear",
      "album": "u love u (with Tate McRae)",
      "track": "u love u (with Tate McRae)",
      "uri": "spotify:track:4RCpHnkhMmm67EKbI4aEO7"
    },
    {
      "artist": "Sam Smith",
      "album": "In The Lonely Hour",
      "track": "Like I Can",
      "uri": "spotify:track:2TeLIzFBe3hxkPR5FIQZut"
    },
    {
      "artist": "Polo G",
      "album": "Die A Legend",
      "track": "Pop Out (feat. Lil Tjay)",
      "uri": "spotify:track:6uFn47ACjqYkc0jADwEdj1"
    },
    {
      "artist": "Pritam",
      "album": "Yeh Jawaani Hai Deewani",
      "track": "Dilliwaali Girlfriend",
      "uri": "spotify:track:3W1XPf7mvuQcWQB7U7MbTM"
    },
    {
      "artist": "Charlie Puth",
      "album": "Light Switch",
      "track": "Light Switch",
      "uri": "spotify:track:3AVXwaOGCEL8cmBecfcsFJ"
    },
    {
      "artist": "Bruno Mars",
      "album": "Finesse (Remix) [feat. Cardi B]",
      "track": "Finesse - Remix; feat. Cardi B",
      "uri": "spotify:track:3Vo4wInECJQuz9BIBMOu8i"
    },
    {
      "artist": "Justin Bieber",
      "album": "My World",
      "track": "Love Me",
      "uri": "spotify:track:0yIywEquxORnu1dR0WYsdN"
    },
    {
      "artist": "Drake",
      "album": "Dark Lane Demo Tapes",
      "track": "Chicago Freestyle (feat. Giveon)",
      "uri": "spotify:track:4wVOKKEHUJxHCFFNUWDn0B"
    },
    {
      "artist": "Quinn XCII",
      "album": "From Michigan With Love",
      "track": "Autopilot",
      "uri": "spotify:track:5yU3w1RzMZpSWytWAU9iyN"
    },
    {
      "artist": "blackbear",
      "album": "digital druglord",
      "track": "wish u the best (feat. Stalking Gia)",
      "uri": "spotify:track:2O30HZ3iEz32Nx8yVMJjFO"
    },
    {
      "artist": "Tyler James Williams",
      "album": "Let It Shine",
      "track": "Don't Run Away",
      "uri": "spotify:track:5BgPiQZiSUR0IpflMDJwzq"
    },
    {
      "artist": "Jack Harlow",
      "album": "Confetti",
      "track": "THRU THE NIGHT (feat. Bryson Tiller)",
      "uri": "spotify:track:1AgSUWSzmza5jF6ER5R68v"
    },
    {
      "artist": "Mac Miller",
      "album": "K.I.D.S.",
      "track": "The Spins",
      "uri": "spotify:track:51pshtuYkgUQnt5huMPbKL"
    },
    {
      "artist": "YG",
      "album": "Scared Money",
      "track": "Scared Money (feat. J. Cole and Moneybagg Yo)",
      "uri": "spotify:track:4heBcjj4Lw3X2sQVFNbLbz"
    },
    {
      "artist": "Taylor Swift",
      "album": "reputation",
      "track": "Don’t Blame Me",
      "uri": "spotify:track:1R0a2iXumgCiFb7HEZ7gUE"
    },
    {
      "artist": "Giveon",
      "album": "For Tonight",
      "track": "For Tonight",
      "uri": "spotify:track:61Emqg95O9zo1GNOcyxq4Y"
    },
    {
      "artist": "Clinton Kane",
      "album": "GO TO HELL",
      "track": "GO TO HELL",
      "uri": "spotify:track:55XRXhQeU25IwqVpjQqxkz"
    },
    {
      "artist": "Kodak Black",
      "album": "Sniper Gang Presents Syko Bob & Snapkatt: Nightmare Babies",
      "track": "Super Gremlin",
      "uri": "spotify:track:4A8cWXxKfIL3lAyUDzXbCF"
    },
    {
      "artist": "Mac Miller",
      "album": "Macadelic",
      "track": "Fight the Feeling",
      "uri": "spotify:track:2w9htZtkcbR48NCWzXjfvb"
    },
    {
      "artist": "Kanye West",
      "album": "My Beautiful Dark Twisted Fantasy",
      "track": "Runaway",
      "uri": "spotify:track:3DK6m7It6Pw857FcQftMds"
    },
    {
      "artist": "Megan Thee Stallion",
      "album": "Good News",
      "track": "Body",
      "uri": "spotify:track:0A1hoCfMLkiAgvhWkkucJa"
    },
    {
      "artist": "Hannah Montana",
      "album": "Hannah Montana Forever",
      "track": "Ordinary Girl",
      "uri": "spotify:track:2kIq7Oq6YNfdUuTrmPC4w1"
    },
    {
      "artist": "Luis Fonsi",
      "album": "VIDA",
      "track": "Échame La Culpa",
      "uri": "spotify:track:0mlAOSILGRys2IbvyOT5VJ"
    },
    {
      "artist": "Hannah Montana",
      "album": "Hannah Montana Forever",
      "track": "Are You Ready",
      "uri": "spotify:track:3zsz2vU6phbgWu3eFEnLHz"
    },
    {
      "artist": "Russ",
      "album": "There's Really A Wolf",
      "track": "Losin Control",
      "uri": "spotify:track:4cxMGhkinTocPSVVKWIw0d"
    },
    {
      "artist": "Little Mix",
      "album": "Glory Days",
      "track": "Touch (feat. Kid Ink)",
      "uri": "spotify:track:3TdXFHsGYGYEYP6Kg3he9W"
    },
    {
      "artist": "Lil Tjay",
      "album": "Destined 2 Win",
      "track": "Headshot (feat. Polo G & Fivio Foreign)",
      "uri": "spotify:track:4eNOLmx8r2IJAVKvBBL1jv"
    },
    {
      "artist": "Eminem",
      "album": "The Eminem Show",
      "track": "'Till I Collapse",
      "uri": "spotify:track:4xkOaSrkexMciUUogZKVTS"
    },
    {
      "artist": "Justin Bieber",
      "album": "Never Say Never - The Remixes",
      "track": "Never Say Never",
      "uri": "spotify:track:5GYbkDveRD2I8M5ZJ14hWn"
    },
    {
      "artist": "Lexi Jayde",
      "album": "drunk text me",
      "track": "drunk text me",
      "uri": "spotify:track:2tbu7dOzCjM5JrPGr0sIes"
    },
    {
      "artist": "grentperez",
      "album": "Cherry Wine",
      "track": "Cherry Wine",
      "uri": "spotify:track:1a1LrfgkTvfHFykIxcv8WU"
    },
    {
      "artist": "Summer Walker",
      "album": "Still Over It",
      "track": "Ex For A Reason (with JT from City Girls)",
      "uri": "spotify:track:1De7cOMrdUnVpjWBaowMg4"
    },
    {
      "artist": "Maroon 5",
      "album": "V",
      "track": "Maps",
      "uri": "spotify:track:4gbVRS8gloEluzf0GzDOFc"
    },
    {
      "artist": "Future",
      "album": "Future & Juice WRLD Present... WRLD ON DRUGS",
      "track": "Fine China",
      "uri": "spotify:track:5274I4mUMnYczyeXkGDWZN"
    },
    {
      "artist": "Jay Park",
      "album": "EVERYTHING YOU WANTED",
      "track": "All I Wanna Do (K) (Feat. Hoody & Loco)",
      "uri": "spotify:track:2FWquqPNxte8iqZ3ATQG0p"
    },
    {
      "artist": "Carrie Underwood",
      "album": "Cry Pretty",
      "track": "The Champion - Bonus Track",
      "uri": "spotify:track:2F6JxWMP2ZfmVErc3ZTmqQ"
    },
    {
      "artist": "Little Mix",
      "album": "Glory Days",
      "track": "Oops (feat. Charlie Puth)",
      "uri": "spotify:track:7uU7UhUzfZJ5vEMoemdcIW"
    },
    {
      "artist": "Lil Tjay",
      "album": "Destined 2 Win",
      "track": "Calling My Phone",
      "uri": "spotify:track:3J8EOeKLTLXORtWPpOU5bE"
    },
    {
      "artist": "Baby Keem",
      "album": "family ties (with Kendrick Lamar)",
      "track": "family ties (with Kendrick Lamar)",
      "uri": "spotify:track:7Bpx2vsWfQFBACRz4h3IqH"
    },
    {
      "artist": "Kanye West",
      "album": "The Life Of Pablo",
      "track": "Saint Pablo",
      "uri": "spotify:track:1o0kWPueYo94LIjPYOE5Nf"
    },
    {
      "artist": "Stephen Sanchez",
      "album": "Until I Found You",
      "track": "Until I Found You",
      "uri": "spotify:track:0T5iIrXA4p5GsubkhuBIKV"
    },
    {
      "artist": "Jack Harlow",
      "album": "Come Home The Kids Miss You",
      "track": "Dua Lipa",
      "uri": "spotify:track:0LnS7aOdOdI1dNKZqdOLz4"
    },
    {
      "artist": "Pop Smoke",
      "album": "Meet The Woo 2",
      "track": "Element",
      "uri": "spotify:track:57BGVV6wcyhbn3hsjlqEZB"
    },
    {
      "artist": "Justin Bieber",
      "album": "My World",
      "track": "One Time",
      "uri": "spotify:track:6eDApnV9Jdb1nYahOlbbUh"
    },
    {
      "artist": "Trippie Redd",
      "album": "LIFE'S A TRIP",
      "track": "Taking A Walk",
      "uri": "spotify:track:4mHgYpuGHu99Mw69E83CP2"
    },
    {
      "artist": "Future",
      "album": "Pluto x Baby Pluto (Deluxe)",
      "track": "Tic Tac",
      "uri": "spotify:track:0anUgBvnA4u5LsHUeLRprc"
    },
    {
      "artist": "Kanye West",
      "album": "My Beautiful Dark Twisted Fantasy",
      "track": "Blame Game",
      "uri": "spotify:track:4EndPA8b6FDWYp1RgsnLEB"
    },
    {
      "artist": "Taylor Swift",
      "album": "Red (Taylor's Version)",
      "track": "Girl At Home (Taylor's Version)",
      "uri": "spotify:track:0DMVrlMUn01M0IcpDbwgu7"
    },
    {
      "artist": "Tate McRae",
      "album": "stupid",
      "track": "stupid",
      "uri": "spotify:track:4k3uABcX9iaGlt5pRJhumi"
    },
    {
      "artist": "Migos",
      "album": "No Label II",
      "track": "Fight Night",
      "uri": "spotify:track:2n5gVJ9fzeX2SSWlLQuyS9"
    },
    {
      "artist": "Charlie Puth",
      "album": "Cheating on You",
      "track": "Cheating on You",
      "uri": "spotify:track:0ClPIeT6MSgfSgQ9ZrJbAq"
    },
    {
      "artist": "PRETTYMUCH",
      "album": "Phases",
      "track": "Phases",
      "uri": "spotify:track:3je88Q4OvTqIx7BFRFYvRA"
    },
    {
      "artist": "Maroon 5",
      "album": "Songs About Jane: 10th Anniversary Edition",
      "track": "This Love",
      "uri": "spotify:track:6ECp64rv50XVz93WvxXMGF"
    },
    {
      "artist": "Selena Gomez",
      "album": "Rare",
      "track": "Crowded Room (feat. 6LACK)",
      "uri": "spotify:track:2C0hTkdEoikhKzDCJl32QZ"
    },
    {
      "artist": "Tyler, The Creator",
      "album": "CALL ME IF YOU GET LOST",
      "track": "WUSYANAME (feat. Youngboy Never Broke Again & Ty Dolla $ign)",
      "uri": "spotify:track:5B0kgjHULYJhAQkK5XsMoC"
    },
    {
      "artist": "Future",
      "album": "Pluto x Baby Pluto",
      "track": "Drankin N Smokin",
      "uri": "spotify:track:0k7wmahjkn389wAZdz19Cv"
    },
    {
      "artist": "Polo G",
      "album": "Distraction",
      "track": "Distraction",
      "uri": "spotify:track:1oc92BMKYkNxK17C2GtyRM"
    },
    {
      "artist": "Meek Mill",
      "album": "Dreams Worth More Than Money",
      "track": "R.I.C.O. (feat. Drake)",
      "uri": "spotify:track:0Y0TOsE1q11qgbi7c5WZsG"
    },
    {
      "artist": "Kanye West",
      "album": "My Beautiful Dark Twisted Fantasy",
      "track": "POWER",
      "uri": "spotify:track:2gZUPNdnz5Y45eiGxpHGSc"
    },
    {
      "artist": "Destiny's Child",
      "album": "Survivor",
      "track": "Survivor",
      "uri": "spotify:track:2Mpj1Ul5OFPyyP4wB62Rvi"
    },
    {
      "artist": "Camila Cabello",
      "album": "Bam Bam (feat. Ed Sheeran)",
      "track": "Bam Bam (feat. Ed Sheeran)",
      "uri": "spotify:track:0QBzMgT7NIeoCYy3sJCof1"
    },
    {
      "artist": "Quinn XCII",
      "album": "The Story of Us",
      "track": "Worst",
      "uri": "spotify:track:3bBcJ5L26TPFKFhl2b0jrw"
    },
    {
      "artist": "Chris Brown",
      "album": "Exclusive",
      "track": "With You",
      "uri": "spotify:track:1j3H54xdahpAkNI0q6S89q"
    },
    {
      "artist": "Taylor Swift",
      "album": "Lover",
      "track": "The Man",
      "uri": "spotify:track:3RauEVgRgj1IuWdJ9fDs70"
    },
    {
      "artist": "Polo G",
      "album": "Hall of Fame",
      "track": "RAPSTAR",
      "uri": "spotify:track:18vXApRmJSgQ6wG2ll9AOg"
    },
    {
      "artist": "Justin Bieber",
      "album": "My World",
      "track": "One Less Lonely Girl",
      "uri": "spotify:track:69ghzc538EQSVon2Gm3wrr"
    },
    {
      "artist": "Drake",
      "album": "Views",
      "track": "Feel No Ways",
      "uri": "spotify:track:3cjF2OFRmip8spwZYQRKxP"
    },
    {
      "artist": "Jay Park",
      "album": "Worldwide",
      "track": "MOMMAE",
      "uri": "spotify:track:1LNlfvPQmB0cqYJQQskZ8x"
    },
    {
      "artist": "iann dior",
      "album": "I'm Gone",
      "track": "Pretty Girls",
      "uri": "spotify:track:3fKdTr6Uv8HTb92Ih3QWxa"
    },
    {
      "artist": "Little Mix",
      "album": "Glory Days",
      "track": "Shout Out to My Ex",
      "uri": "spotify:track:0ErK6K0kYr0Ow2RkPMhmMs"
    },
    {
      "artist": "Summer Walker",
      "album": "Still Over It",
      "track": "Insane",
      "uri": "spotify:track:3pcxxaUxAMSfz2zgetHydD"
    },
    {
      "artist": "Meek Mill",
      "album": "Championships",
      "track": "Almost Slipped",
      "uri": "spotify:track:1bx4Jw8A7GQtImIQGccI6D"
    },
    {
      "artist": "Hannah Montana",
      "album": "Hannah Montana Forever",
      "track": "Kiss it Goodbye",
      "uri": "spotify:track:4SdR86EedszvIrLBTMKi3b"
    },
    {
      "artist": "Lil Tecca",
      "album": "Virgo World",
      "track": "When You Down (with Polo G feat. Lil Durk)",
      "uri": "spotify:track:5kTn07V96U8LyoQgz6DZzX"
    },
    {
      "artist": "Charlie Puth",
      "album": "Light Switch",
      "track": "Light Switch",
      "uri": "spotify:track:1BSMpVGWs3v5BZKnAQziAc"
    },
    {
      "artist": "Tate McRae",
      "album": "slower",
      "track": "slower",
      "uri": "spotify:track:1bd4heB3yXc5iFTPoOMPuo"
    },
    {
      "artist": "Lil Tjay",
      "album": "True 2 Myself",
      "track": "Leaked",
      "uri": "spotify:track:0W64NfLrIsRTAFObko6uJx"
    },
    {
      "artist": "Billie Eilish",
      "album": "Happier Than Ever",
      "track": "Happier Than Ever - Edit",
      "uri": "spotify:track:32BeYxKPrig1LefHsC0Xuo"
    },
    {
      "artist": "A Boogie Wit da Hoodie",
      "album": "Hoodie SZN",
      "track": "Love Drugs and Sex",
      "uri": "spotify:track:1Gno5IBUHh6vUKp4nxu2Yd"
    },
    {
      "artist": "Mustard",
      "album": "Cold Summer",
      "track": "Want Her",
      "uri": "spotify:track:4zrwPfq5ENLzjq41Txs2HR"
    },
    {
      "artist": "Jack Harlow",
      "album": "First Class",
      "track": "First Class",
      "uri": "spotify:track:1rDQ4oMwGJI7B4tovsBOxc"
    },
    {
      "artist": "Tate McRae",
      "album": "she's all i wanna be",
      "track": "she's all i wanna be",
      "uri": "spotify:track:0IuVhCflrQPMGRrOyoY5RW"
    },
    {
      "artist": "Megan Thee Stallion",
      "album": "Suga",
      "track": "Ain't Equal",
      "uri": "spotify:track:29HQG5FmpUH5nWwHDF163B"
    },
    {
      "artist": "Nicki Minaj",
      "album": "The Pinkprint",
      "track": "The Night Is Still Young",
      "uri": "spotify:track:4bBrKDo8rchikwZOtmXbIH"
    },
    {
      "artist": "Jay Park",
      "album": "Evolution",
      "track": "So Good",
      "uri": "spotify:track:5xv7er3pGCd8ZDco5H8SPN"
    },
    {
      "artist": "Pharrell Williams",
      "album": "Just A Cloud Away",
      "track": "Just A Cloud Away",
      "uri": "spotify:track:0DGTcMqvVR7fmBXgiG6jz4"
    },
    {
      "artist": "The Kid LAROI",
      "album": "Thousand Miles",
      "track": "Thousand Miles",
      "uri": "spotify:track:1r8ZCjfrQxoy2wVaBUbpwg"
    },
    {
      "artist": "Childish Gambino",
      "album": "Because the Internet",
      "track": "3005",
      "uri": "spotify:track:2ZltjIqztEpZtafc8w0I9t"
    },
    {
      "artist": "Quinn XCII",
      "album": "Bloom",
      "track": "Light On",
      "uri": "spotify:track:5Px9T2xZU1yLXga0JrEHI6"
    },
    {
      "artist": "H.E.R.",
      "album": "Back of My Mind",
      "track": "Come Through (feat. Chris Brown)",
      "uri": "spotify:track:29he0Joo5sz2607A6ZBT6H"
    },
    {
      "artist": "Kanye West",
      "album": "Donda",
      "track": "Praise God",
      "uri": "spotify:track:0WSEq9Ko4kFPt8yo3ICd6T"
    },
    {
      "artist": "Kanye West",
      "album": "Graduation",
      "track": "I Wonder",
      "uri": "spotify:track:4jQqM4NI79HEcWHUJb8Hvf"
    },
    {
      "artist": "Eminem",
      "album": "The Eminem Show",
      "track": "White America",
      "uri": "spotify:track:15qrWkkYCfmtu1uRpGf48L"
    },
    {
      "artist": "Olivia Rodrigo",
      "album": "good 4 u",
      "track": "good 4 u",
      "uri": "spotify:track:6PERP62TejQjgHu81OHxgM"
    },
    {
      "artist": "The Kid LAROI",
      "album": "Fade Away",
      "track": "Fade Away",
      "uri": "spotify:track:32ypPhtgTaETvFn3ZIHXTW"
    },
    {
      "artist": "BLACKPINK",
      "album": "As If It's Your Last",
      "track": "As If It's Your Last",
      "uri": "spotify:track:4ZxOuNHhpyOj4gv52MtQpT"
    },
    {
      "artist": "The Kid LAROI",
      "album": "F*CK LOVE (SAVAGE)",
      "track": "SO DONE",
      "uri": "spotify:track:2gqWRRCXnma9L8xQ1RdemQ"
    },
    {
      "artist": "(G)I-DLE",
      "album": "I am",
      "track": "LATATA",
      "uri": "spotify:track:2ezKXygNO30pXyDQXkm6oD"
    },
    {
      "artist": "Conan Gray",
      "album": "Kid Krow",
      "track": "Maniac",
      "uri": "spotify:track:6KfoDhO4XUWSbnyKjNp9c4"
    },
    {
      "artist": "Katy Perry",
      "album": "Teenage Dream: The Complete Confection",
      "track": "Teenage Dream",
      "uri": "spotify:track:55qBw1900pZKfXJ6Q9A2Lc"
    },
    {
      "artist": "Kanye West",
      "album": "Graduation",
      "track": "Good Life",
      "uri": "spotify:track:3GVttx9eVHDl1v1BTGFcTI"
    },
    {
      "artist": "Eminem",
      "album": "The Eminem Show",
      "track": "Say Goodbye Hollywood",
      "uri": "spotify:track:288e3FhmVuCqPmNEfAH0h6"
    },
    {
      "artist": "Flo Rida",
      "album": "Mail on Sunday",
      "track": "In the Ayer (feat. will.I.am)",
      "uri": "spotify:track:6RpiAj9Ofv0Uqp6n2OuRoh"
    },
    {
      "artist": "Kanye West",
      "album": "JESUS IS KING",
      "track": "Follow God",
      "uri": "spotify:track:2QpGZOhTCHHiKmpSO9FW4h"
    },
    {
      "artist": "Kanye West",
      "album": "My Beautiful Dark Twisted Fantasy",
      "track": "All Of The Lights",
      "uri": "spotify:track:22L7bfCiAkJo5xGSQgmiIO"
    },
    {
      "artist": "Quinn XCII",
      "album": "The Story of Us",
      "track": "Always Been You",
      "uri": "spotify:track:7cWyFwAaxdK2HSRuiRkMjy"
    },
    {
      "artist": "21 Savage",
      "album": "SAVAGE MODE II",
      "track": "Rich Nigga Shit (feat. Young Thug)",
      "uri": "spotify:track:3ruoIF2UnoXdzK8mR61ebq"
    },
    {
      "artist": "Marshmello",
      "album": "Numb",
      "track": "Numb",
      "uri": "spotify:track:10xV5l9nhLvFpR8mqzs0bL"
    },
    {
      "artist": "Megan Thee Stallion",
      "album": "Suga",
      "track": "Crying In The Car",
      "uri": "spotify:track:3OxwuE0500Qzobf7uykMzy"
    },
    {
      "artist": "Taylor Swift",
      "album": "Red (Taylor's Version)",
      "track": "I Almost Do (Taylor's Version)",
      "uri": "spotify:track:2r9CbjYgFhtAmcFv1cSquB"
    },
    {
      "artist": "Harry Styles",
      "album": "As It Was",
      "track": "As It Was",
      "uri": "spotify:track:4LRPiXqCikLlN15c3yImP7"
    },
    {
      "artist": "Taylor Swift",
      "album": "1989",
      "track": "New Romantics",
      "uri": "spotify:track:6rZVy6FIG7lSJQMFXHo12z"
    },
    {
      "artist": "Drake",
      "album": "More Life",
      "track": "Teenage Fever",
      "uri": "spotify:track:6n3HGiq4v35D6eFOSwqYuo"
    },
    {
      "artist": "Deno",
      "album": "Boy Meets World",
      "track": "Lingo",
      "uri": "spotify:track:5kXCqr2WpJvEm23EARwLuK"
    },
    {
      "artist": "Kanye West",
      "album": "Donda",
      "track": "Jail",
      "uri": "spotify:track:6d8HN8MqqbqrEUI2bvx0aG"
    },
    {
      "artist": "Oliver Tree",
      "album": "Life Goes On (feat. Trippie Redd & Ski Mask The Slump God)",
      "track": "Life Goes On (feat. Trippie Redd & Ski Mask The Slump God)",
      "uri": "spotify:track:07ShpyCaAqfCseA3fWFFMY"
    },
    {
      "artist": "Kanye West",
      "album": "My Beautiful Dark Twisted Fantasy",
      "track": "Devil In A New Dress",
      "uri": "spotify:track:1UGD3lW3tDmgZfAVDh6w7r"
    },
    {
      "artist": "Shaggy",
      "album": "Hot Shot",
      "track": "It Wasn't Me",
      "uri": "spotify:track:4GFJRLgxy4chyfWqfPTJaI"
    },
    {
      "artist": "Taylor Swift",
      "album": "Lover",
      "track": "Paper Rings",
      "uri": "spotify:track:4y5bvROuBDPr5fuwXbIBZR"
    },
    {
      "artist": "DVBBS",
      "album": "West Coast (feat. Quinn XCII)",
      "track": "West Coast (feat. Quinn XCII)",
      "uri": "spotify:track:4fCE1SCDulouoac9Q8XroU"
    },
    {
      "artist": "Quinn XCII",
      "album": "Change of Scenery II",
      "track": "We Don’t Talk Enough (with Alexander 23)",
      "uri": "spotify:track:4IaizE26moyyMYn70TeFiX"
    },
    {
      "artist": "J. Cole",
      "album": "The Off-Season",
      "track": "m y . l i f e (with 21 Savage & Morray)",
      "uri": "spotify:track:1D3z6HTiQsNmZxjl7F7eoG"
    },
    {
      "artist": "Clinton Kane",
      "album": "Fix It to Break It",
      "track": "Fix It to Break It",
      "uri": "spotify:track:1uviKYHZuM4uINK33F7sCt"
    },
    {
      "artist": "Kanye West",
      "album": "Graduation",
      "track": "Good Life",
      "uri": "spotify:track:14blxrgE0VWAgv5aF2wWmx"
    },
    {
      "artist": "Drake",
      "album": "Certified Lover Boy",
      "track": "Girls Want Girls (with Lil Baby)",
      "uri": "spotify:track:37Nqx7iavZpotJSDXZWbJ3"
    },
    {
      "artist": "Taylor Swift",
      "album": "Red (Taylor's Version)",
      "track": "I Bet You Think About Me (feat. Chris Stapleton) (Taylor’s Version) (From The Vault)",
      "uri": "spotify:track:4CkgMiMqZ5JzW9iYXSTMTL"
    },
    {
      "artist": "Camila Cabello",
      "album": "Romance",
      "track": "Liar",
      "uri": "spotify:track:073ILU1C3APNRGF66VhtyA"
    },
    {
      "artist": "M. Pokora",
      "album": "PYRAMIDE",
      "track": "Tombé",
      "uri": "spotify:track:3EiDyqPIjDDo6F8RS5Lj4t"
    },
    {
      "artist": "Jack Harlow",
      "album": "Sweet Action",
      "track": "I WANNA SEE SOME ASS (feat. jetsonmade)",
      "uri": "spotify:track:2aWVaW1p2kUc5yuKwBmRJi"
    },
    {
      "artist": "Kanye West",
      "album": "808s & Heartbreak",
      "track": "Love Lockdown",
      "uri": "spotify:track:2UNedS0c7DmhV7q6CnwcmT"
    },
    {
      "artist": "HoodRich Pablo Juan",
      "album": "Designer Drugz 3",
      "track": "We Don't Luv Em",
      "uri": "spotify:track:7Ay41oJQbfdIrhfNy46PuD"
    },
    {
      "artist": "Pritam",
      "album": "Yeh Jawaani Hai Deewani",
      "track": "Badtameez Dil",
      "uri": "spotify:track:4eu27jAU2bbnyHUC3G75U8"
    },
    {
      "artist": "The Chainsmokers",
      "album": "High",
      "track": "High",
      "uri": "spotify:track:3t4KHjd8uQpJJ2fa0fRIpR"
    },
    {
      "artist": "Polo G",
      "album": "Hall of Fame",
      "track": "Toxic",
      "uri": "spotify:track:3h3NKhcfHkr6GvEpC3FRI5"
    },
    {
      "artist": "Meek Mill",
      "album": "Championships",
      "track": "Uptown Vibes (feat. Fabolous & Anuel AA)",
      "uri": "spotify:track:2tnlNVAhuQGgoFJxALVeXx"
    },
    {
      "artist": "Katy Perry",
      "album": "Teenage Dream: The Complete Confection",
      "track": "The One That Got Away",
      "uri": "spotify:track:3oL3XRtkP1WVbMxf7dtTdu"
    },
    {
      "artist": "Taylor Swift",
      "album": "Red (Taylor's Version)",
      "track": "Babe (Taylor's Version) (From The Vault)",
      "uri": "spotify:track:0v4z1tuZvn6LGknom9Qx7d"
    },
    {
      "artist": "Kid Cudi",
      "album": "Man On The Moon II: The Legend Of Mr. Rager",
      "track": "Mr. Rager",
      "uri": "spotify:track:2ncLdwTd8qzkxiJjlbiOgC"
    },
    {
      "artist": "J. Cole",
      "album": "2014 Forest Hills Drive",
      "track": "January 28th",
      "uri": "spotify:track:6NyhBA9M6KK0fuVsojxL00"
    },
    {
      "artist": "Lil Baby",
      "album": "Street Gossip",
      "track": "Ready (feat. Gunna)",
      "uri": "spotify:track:4F6yN5FsFW10Ucx7cLCzBh"
    },
    {
      "artist": "G.R.L.",
      "album": "G.R.L.",
      "track": "Show Me What You Got",
      "uri": "spotify:track:4lXMjXH76wpfqu0XIw3YOl"
    },
    {
      "artist": "A$AP Rocky",
      "album": "Sundress",
      "track": "Sundress",
      "uri": "spotify:track:2aPTvyE09vUCRwVvj0I8WK"
    },
    {
      "artist": "Meek Mill",
      "album": "Championships",
      "track": "Dangerous (feat. Jeremih and PnB Rock)",
      "uri": "spotify:track:3lb5fWSG2p7x8ik8HN9oFR"
    },
    {
      "artist": "Camila Cabello",
      "album": "Familia",
      "track": "Bam Bam (feat. Ed Sheeran)",
      "uri": "spotify:track:3lDSWvR0FXWGXo7mhDUs3v"
    },
    {
      "artist": "benny blanco",
      "album": "FRIENDS KEEP SECRETS",
      "track": "Eastside (with Halsey & Khalid)",
      "uri": "spotify:track:7FGq80cy8juXBCD2nrqdWU"
    },
    {
      "artist": "The Vamps",
      "album": "Night & Day",
      "track": "All Night",
      "uri": "spotify:track:0dXNQ8dckG4eYfEtq9zcva"
    },
    {
      "artist": "iann dior",
      "album": "Still Here",
      "track": "shots in the dark (with Trippie Redd)",
      "uri": "spotify:track:03m2VS3eYqKwbHvEykTYl5"
    },
    {
      "artist": "Scorey",
      "album": "Catch Me If You Can",
      "track": "Love Letter",
      "uri": "spotify:track:2MPfWVq2YFGdNTSLoj4RgA"
    },
    {
      "artist": "blackbear",
      "album": "everything means nothing",
      "track": "I feel bad",
      "uri": "spotify:track:1OkIpW255qLxswGyjgUL5x"
    },
    {
      "artist": "Conan Gray",
      "album": "Kid Krow",
      "track": "Wish You Were Sober",
      "uri": "spotify:track:0kn2gu8Pd03DiYHzRvX2Xk"
    },
    {
      "artist": "Taylor Swift",
      "album": "Lover",
      "track": "Lover",
      "uri": "spotify:track:1dGr1c8CrMLDpV6mPbImSI"
    },
    {
      "artist": "Megan Thee Stallion",
      "album": "Sweetest Pie",
      "track": "Sweetest Pie",
      "uri": "spotify:track:7mFj0LlWtEJaEigguaWqYh"
    },
    {
      "artist": "Camila Cabello",
      "album": "Familia",
      "track": "Don't Go Yet",
      "uri": "spotify:track:49dBB2KMMmsSCIGVwwH0v3"
    },
    {
      "artist": "21 Savage",
      "album": "i am > i was",
      "track": "ball w/o you",
      "uri": "spotify:track:50a8bKqlwDEqeiEknrzkTO"
    },
    {
      "artist": "Bruno Mars",
      "album": "Doo-Wops & Hooligans",
      "track": "Runaway Baby",
      "uri": "spotify:track:7hCNBVRhHzcsRAv0TQnOzq"
    },
    {
      "artist": "Bazzi",
      "album": "I Like That",
      "track": "I Like That",
      "uri": "spotify:track:2RkZZh5XQ4y3sG8gCu96Tz"
    },
    {
      "artist": "Young Thug",
      "album": "So Much Fun",
      "track": "Bad Bad Bad (feat. Lil Baby)",
      "uri": "spotify:track:1GeNui6m825V8jP4uKiIaH"
    },
    {
      "artist": "Chief Keef",
      "album": "Finally Rich",
      "track": "I Don't Like",
      "uri": "spotify:track:1h6kgem1ai8vUgO1rZOwfB"
    },
    {
      "artist": "Summer Walker",
      "album": "Still Over It",
      "track": "No Love (with SZA)",
      "uri": "spotify:track:08SB2OtZkaliju77WYEKxk"
    },
    {
      "artist": "Hannah Montana",
      "album": "Hannah Montana Forever",
      "track": "I'll Always Remember You",
      "uri": "spotify:track:60c0p6GGnuwdKcQnmuM2zC"
    },
    {
      "artist": "Jhené Aiko",
      "album": "Trip",
      "track": "Sativa",
      "uri": "spotify:track:2pg2TiYo9Rb8KeB5JjP7jS"
    },
    {
      "artist": "T-Pain",
      "album": "Epiphany",
      "track": "Buy U a Drank (Shawty Snappin') (feat. Yung Joc)",
      "uri": "spotify:track:2aIdVb8v9KTpEZnftkz2mD"
    },
    {
      "artist": "Post Malone",
      "album": "Hollywood's Bleeding",
      "track": "Die For Me (feat. Future & Halsey)",
      "uri": "spotify:track:2C6WXnmZ66tHhHlnvwePiK"
    },
    {
      "artist": "Alec Benjamin",
      "album": "These Two Windows",
      "track": "Alamo",
      "uri": "spotify:track:1HcKi5Ld0B09KQeLBa4FJa"
    }
  ]
}

